{
    "key": "group_5bc497dfa43f7",
    "title": "Block: Testimonial",
    "location": [
        [
            {
                "param": "block",
                "operator": "==",
                "value": "acf\/testimonial"
            }
        ]
    ],
    "menu_order": 0,
    "position": "normal",
    "style": "default",
    "label_placement": "top",
    "instruction_placement": "label",
    "hide_on_screen": "",
    "active": 1,
    "description": "",
    "fields": [
        {
            "key": "field_5bc497ef95c40",
            "label": "Avatar",
            "name": "avatar",
            "type": "image",
            "instructions": "",
            "required": 0,
            "conditional_logic": 0,
            "wrapper": {
                "width": "",
                "class": "",
                "id": ""
            },
            "return_format": "url",
            "preview_size": "thumbnail",
            "library": "all",
            "min_width": "",
            "min_height": "",
            "min_size": "",
            "max_width": "",
            "max_height": "",
            "max_size": "",
            "mime_types": ""
        },
        {
            "key": "field_5bc4980795c41",
            "label": "Author",
            "name": "author",
            "type": "text",
            "instructions": "",
            "required": 0,
            "conditional_logic": 0,
            "wrapper": {
                "width": "",
                "class": "",
                "id": ""
            },
            "default_value": "",
            "placeholder": "",
            "prepend": "",
            "append": "",
            "maxlength": ""
        },
        {
            "key": "field_5bc4980f95c42",
            "label": "Testimonial",
            "name": "testimonial",
            "type": "textarea",
            "instructions": "",
            "required": 0,
            "conditional_logic": 0,
            "wrapper": {
                "width": "",
                "class": "",
                "id": ""
            },
            "default_value": "",
            "placeholder": "",
            "maxlength": "",
            "rows": "",
            "new_lines": ""
        },
        {
            "key": "field_5bc4981a95c43",
            "label": "Background Color",
            "name": "background_color",
            "type": "color_picker",
            "instructions": "",
            "required": 0,
            "conditional_logic": 0,
            "wrapper": {
                "width": "",
                "class": "",
                "id": ""
            },
            "default_value": ""
        },
        {
            "key": "field_5bc4982495c44",
            "label": "Text Color",
            "name": "text_color",
            "type": "color_picker",
            "instructions": "",
            "required": 0,
            "conditional_logic": 0,
            "wrapper": {
                "width": "",
                "class": "",
                "id": ""
            },
            "default_value": ""
        }
    ],
    "modified": 1539611103
}